Workbook

Sheet Transactions
A1: transaction_id | B1: branch_code | C1: date_of_sale | D1: staff_id | E1: product_category | F1: product_name | G1: quantity | H1: unit_price | I1: discount_applied | J1: payment_type | K1: customer_type | L1: total_sale | M1: returned
A2: 5453 | B2: BR02 | C2: 24/1/2024 | D2: S006 | E2: Electronics | F2: Bluetooth Speaker | G2: 5 | H2: N/A | I2: 0% | J2: Card | K2: RETURNING | M2: no
A3: 5302 | B3: BR01 | C3: 18-Jan-24 | D3: S002 | E3: Home & Kitchen | F3: Storage Containers | H3: 10605.57 | I3: None | J3: card | K3: RETURNING | M3: Y
A4: 5026 | B4: BR02 | C4: 9/15/2024 | D4: S005 | E4: Groceries | F4: Spaghetti Pack | H4: ₦8,416.54 | I4: 0% | J4: Card | K4: New | M4: Yes
A5: 5001 | B5: BR02 | C5: 5/8/2024 | D5: S002 | E5: Electronics | F5: HDMI Cable | G5: 5 | H5: N/A | I5: 15% | J5: card | K5: new | M5: Yes
A6: 5380 | B6: BR01 | C6: 22-May-24 | D6: S002 | E6: Home & Kitchen | F6: Blender | G6: 1 | H6: N/A | I6: None | J6: Cash | K6: returning
A7: 5214 | B7: BRXX | C7: 26/8/2024 | D7: S003 | E7: Home & Kitchen | F7: Cutlery Set | H7: 33,815.79 | I7: 5% | J7: Cash | K7: returning | M7: Yes
A8: 5410 | B8: BR04 | C8: 16/8/2024 | D8: S007 | E8: Groceries | F8: Cooking Oil (1L) | G8: 5 | H8: 23072.48 | I8: 0% | J8: Transfer | K8: NEW | M8: no
A9: 5350 | B9: br01 | C9: May 3, 2024 | D9: S006 | E9: Personal Care | F9: Toothpaste | G9: 5 | H9: 32,386.21 | I9: 0% | J9: card | K9: new | M9: N
A10: 5445 | B10: BR05 | C10: 2024-03-06 | D10: S007 | E10: Home & Kitchen | F10: Cutlery Set | G10: 1 | H10: 1,321.59 | I10: 10% | J10: Card | K10: Returning | M10: yes
A11: 5227 | B11: BR05 | C11: 4/6/2024 | D11: S001 | E11: Personal Care | F11: Deodorant | H11: N/A | I11: None | J11: transfer | K11: new | M11: No
A12: 5478 | B12: br03 | C12: 15-Apr-24 | D12: S003 | E12: Electronics | F12: Phone Charger | H12: 26,958.25 | I12: 10% | J12: transfer | K12: Returning | M12: N
A13: 5439 | B13: BR02 | C13: May 8, 2024 | D13: S004 | E13: Personal Care | F13: Toothpaste | G13: 3 | H13: N/A | I13: 5% | J13: CASH | K13: New | M13: no
A14: 5058 | B14: BR01 | C14: September 19, 2024 | D14: S099 | E14: Home & Kitchen | F14: Blender | G14: 3 | H14: N/A | I14: N/A | J14: Cash | K14: New | M14: No
A15: 5384 | B15: BR05 | C15: 6-Apr-24 | D15: S004 | E15: Home & Kitchen | F15: Storage Containers | G15: 2 | H15: 17169.84 | I15: 15% | J15: Transfer | K15: returning | M15: no
A16: 5101 | B16: BR05 | C16: 2024-09-14 | D16: S004 | E16: Personal Care | F16: Deodorant | G16: 3 | H16: 25154.23 | I16: 0% | J16: transfer | K16: Returning | M16: No
A17: 5176 | B17: BR03 | C17: 22-Mar-24 | D17: S100 | E17: Groceries | F17: Tomato Paste | G17: 1 | H17: N/A | I17: 5% | J17: Transfer | K17: Returning | M17: no
A18: 5310 | B18: BR04 | C18: 2024-06-20 | D18: S003 | E18: Groceries | F18: Cooking Oil (1L) | H18: N/A | I18: 10% | J18: CASH | K18: RETURNING | M18: no
A19: 5167 | B19: BR03 | C19: March 31, 2024 | D19: S007 | E19: Groceries | F19: Spaghetti Pack | G19: 1 | H19: 23400.68 | I19: 10% | J19: transfer | K19: New | M19: N
A20: 5217 | B20: BR05 | C20: 26/9/2024 | D20: S003 | E20: Groceries | F20: Tomato Paste | G20: 4 | H20: ₦5,589.59 | I20: None | J20: Cash | K20: RETURNING | M20: Y
A21: 5007 | B21: BR02 | C21: 2024-07-31 | D21: S008 | E21: Electronics | F21: Power Bank | G21: 5 | H21: N/A | J21: Card | K21: NEW | M21: N
A22: 5363 | B22: BR05 | C22: September 18, 2024 | D22: S003 | E22: Home & Kitchen | F22: Kettle | G22: 4 | H22: 37,413.70 | I22: 0% | J22: cash | K22: RETURNING
A23: 5271 | B23: br03 | C23: January 29, 2024 | D23: S004 | E23: Personal Care | F23: Soap Bar | G23: 5 | H23: N/A | I23: 10% | J23: Card | K23: Returning | M23: Y
A24: 5235 | B24: BR03 | C24: 3/29/2024 | D24: S008 | E24: Electronics | F24: HDMI Cable | G24: 1 | H24: 42,907.41 | I24: 5% | J24: Card | K24: New | M24: no
A25: 5116 | B25: br02 | C25: 22/7/2024 | D25: S006 | E25: Groceries | F25: Cooking Oil (1L) | G25: 1 | H25: N/A | I25: 15% | J25: card | K25: Returning | M25: Y
A26: 5353 | B26: BR05 | C26: 18/4/2024 | D26: S008 | E26: Home & Kitchen | F26: Cutlery Set | G26: 1 | H26: N/A | I26: 10% | J26: cash | K26: Returning
A27: 5338 | B27: BR05 | C27: February 21, 2024 | D27: S003 | E27: Groceries | F27: Cooking Oil (1L) | H27: N/A | I27: 10% | J27: Cash | K27: RETURNING | M27: no
A28: 5343 | B28: BR02 | C28: September 22, 2024 | D28: S006 | E28: Electronics | F28: HDMI Cable | G28: 3 | H28: N/A | I28: None | J28: Card | K28: new | M28: No
A29: 5372 | B29: BR01 | C29: 8/24/2024 | D29: S008 | E29: Home & Kitchen | F29: Kettle | G29: 4 | H29: N/A | I29: 5% | J29: Card | K29: returning | M29: yes
A30: 5224 | B30: BR01 | C30: February 1, 2024 | D30: S002 | E30: Personal Care | F30: Soap Bar | G30: 1 | H30: 30,043.06 | I30: N/A | J30: Card | K30: RETURNING
A31: 5205 | B31: BR04 | C31: 2024-01-22 | D31: S008 | E31: Electronics | F31: Power Bank | G31: 3 | H31: ₦27,994.84 | I31: None | J31: transfer | K31: Returning | M31: No
A32: 5305 | B32: BRXX | C32: April 19, 2024 | D32: S002 | E32: Personal Care | F32: Shampoo | G32: 2 | H32: 22,968.48 | I32: N/A | J32: transfer | K32: new | M32: Y
A33: 5210 | B33: br02 | C33: 2024-01-27 | D33: S001 | E33: Groceries | F33: Sugar (1kg) | G33: 3 | H33: 4354.34 | I33: N/A | J33: Transfer | K33: returning | M33: no
A34: 5008 | B34: BR04 | C34: 7/8/2024 | D34: S003 | E34: Groceries | F34: Cooking Oil (1L) | G34: 1 | H34: 22080.84 | I34: 0% | J34: Card | K34: new | M34: no
A35: 5355 | B35: BR05 | C35: 7/6/2024 | D35: S007 | E35: Personal Care | F35: Body Lotion | G35: 5 | H35: ₦25,569.20 | I35: N/A | J35: CASH | K35: Returning | M35: Yes
A36: 5431 | B36: BR05 | C36: 2024-03-01 | D36: S003 | E36: Electronics | F36: HDMI Cable | G36: 2 | H36: ₦36,302.69 | I36: None | J36: Cash | K36: Returning | M36: Yes
A37: 5373 | B37: BR05 | C37: 2024-03-08 | D37: S002 | E37: Personal Care | F37: Deodorant | G37: 1 | H37: 12,020.08 | J37: Cash | K37: Returning
A38: 5402 | B38: BR05 | C38: 2024-02-20 | D38: S006 | E38: Groceries | F38: Cooking Oil (1L) | G38: 1 | H38: 30457.19 | J38: Card | K38: NEW | M38: No
A39: 5394 | B39: BR09 | C39: 3-Feb-24 | D39: S008 | E39: Home & Kitchen | F39: Blender | G39: 5 | H39: N/A | I39: None | J39: cash | K39: Returning | M39: Y
A40: 5103 | B40: br04 | C40: February 12, 2024 | D40: S001 | E40: Groceries | F40: Tomato Paste | H40: N/A | I40: N/A | J40: CARD | K40: RETURNING | M40: N
A41: 5227 | B41: BR05 | C41: 4/6/2024 | D41: S001 | E41: Personal Care | F41: Deodorant | H41: N/A | I41: None | J41: transfer | K41: new | M41: No
A42: 5164 | B42: BR03 | C42: September 26, 2024 | D42: S005 | E42: Groceries | F42: Rice (5kg) | G42: 1 | H42: 1,625.54 | I42: 0% | J42: CASH | K42: new | M42: N
A43: 5171 | B43: BR04 | C43: 9/14/2024 | D43: S004 | E43: Electronics | F43: Phone Charger | G43: 5 | H43: ₦4,070.17 | J43: transfer | K43: new
A44: 5319 | B44: BR04 | C44: 2024-03-23 | D44: S001 | E44: Electronics | F44: HDMI Cable | H44: N/A | I44: 0% | J44: transfer | K44: returning | M44: Y
A45: 5258 | B45: BR02 | C45: 2024-06-07 | D45: S002 | E45: Personal Care | F45: Shampoo | G45: 2 | H45: ₦38,312.98 | I45: 10% | J45: CASH | K45: NEW | M45: No
A46: 5179 | B46: BR01 | C46: May 1, 2024 | D46: S006 | E46: Groceries | F46: Rice (5kg) | G46: 1 | H46: ₦39,321.03 | I46: 0% | J46: cash | K46: Returning
A47: 5068 | B47: BR05 | C47: 20-May-24 | D47: S008 | E47: Personal Care | F47: Toothpaste | H47: N/A | I47: 0% | J47: cash | K47: new | M47: No
A48: 5088 | B48: br02 | C48: August 11, 2024 | D48: S007 | E48: Personal Care | F48: Toothpaste | G48: 1 | H48: N/A | I48: 10% | J48: Card | K48: Returning
A49: 5173 | B49: BR02 | C49: 23/6/2024 | D49: S003 | E49: Home & Kitchen | F49: Non-stick Pan | G49: 2 | H49: 25551.69 | I49: 5% | J49: CASH | K49: RETURNING
A50: 5013 | B50: BR02 | C50: 22/4/2024 | D50: S006 | E50: Electronics | F50: Wireless Earbuds | G50: 4 | H50: 12033.26 | I50: 15% | J50: CASH | K50: NEW | M50: Yes
A51: 5496 | B51: BR02 | C51: January 4, 2024 | D51: S001 | E51: Electronics | F51: Wireless Earbuds | G51: 3 | H51: ₦26,033.94 | I51: 10% | J51: CASH | K51: new | M51: Y
A52: 5473 | B52: BR02 | C52: 2024-04-13 | D52: S006 | E52: Home & Kitchen | F52: Non-stick Pan | H52: N/A | I52: 5% | J52: cash | K52: returning | M52: Yes
A53: 5208 | B53: BR05 | C53: 23/4/2024 | D53: S004 | E53: Home & Kitchen | F53: Kettle | H53: N/A | J53: transfer | K53: New | M53: Yes
A54: 5213 | B54: BR05 | C54: September 11, 2024 | D54: S008 | E54: Groceries | F54: Cooking Oil (1L) | G54: 4 | H54: 38,686.51 | J54: card | K54: Returning | M54: Y
A55: 5109 | B55: br03 | C55: 2024-08-19 | D55: S008 | E55: Home & Kitchen | F55: Cutlery Set | G55: 1 | H55: N/A | I55: 15% | J55: Transfer | K55: Returning
A56: 5178 | B56: BR03 | C56: 2024-03-14 | D56: S008 | E56: Personal Care | F56: Toothpaste | H56: ₦20,943.64 | I56: None | J56: CARD | K56: RETURNING | M56: N
A57: 5456 | B57: BR01 | C57: June 14, 2024 | D57: S007 | E57: Personal Care | F57: Soap Bar | H57: 8059.7 | I57: 15% | J57: Card | K57: New | M57: no
A58: 5065 | B58: BR02 | C58: 7-May-24 | D58: S001 | E58: Personal Care | F58: Shampoo | G58: 4 | H58: 24977.31 | I58: None | J58: Transfer | K58: NEW | M58: Y
A59: 5097 | B59: BR02 | C59: June 1, 2024 | D59: S006 | E59: Groceries | F59: Cooking Oil (1L) | G59: 5 | H59: ₦7,972.12 | I59: None | J59: Card | K59: Returning | M59: N
A60: 5375 | B60: br03 | C60: 13-Sep-24 | D60: S003 | E60: Electronics | F60: Wireless Earbuds | G60: 1 | H60: 44802.54 | I60: None | J60: CARD | K60: returning | M60: no
A61: 5005 | B61: BR02 | C61: 3/2/2024 | D61: S002 | E61: Personal Care | F61: Body Lotion | G61: 5 | H61: ₦22,602.03 | J61: card | K61: NEW | M61: no
A62: 5282 | B62: BR02 | C62: 16/5/2024 | D62: S003 | E62: Groceries | F62: Spaghetti Pack | G62: 3 | H62: 17413.92 | I62: 5% | J62: Cash | K62: RETURNING | M62: yes
A63: 5056 | B63: BR01 | C63: 2024-05-17 | D63: S008 | E63: Groceries | F63: Cooking Oil (1L) | G63: 4 | H63: ₦28,103.69 | J63: cash | K63: NEW | M63: No
A64: 5189 | B64: BR03 | C64: August 23, 2024 | D64: S003 | E64: Electronics | F64: HDMI Cable | G64: 2 | H64: 20,149.29 | I64: None | J64: CASH | K64: Returning | M64: no
A65: 5464 | B65: BR01 | C65: August 17, 2024 | D65: S002 | E65: Personal Care | F65: Deodorant | G65: 4 | H65: N/A | I65: None | J65: CARD | K65: NEW | M65: no
A66: 5121 | B66: br02 | C66: 5/18/2024 | D66: S001 | E66: Groceries | F66: Tomato Paste | G66: 2 | H66: N/A | I66: 15% | J66: Cash | K66: new | M66: Yes
A67: 5325 | B67: BR03 | C67: February 1, 2024 | D67: S003 | E67: Electronics | F67: Power Bank | G67: 3 | H67: 15,467.23 | I67: 15% | J67: Cash | K67: NEW | M67: No
A68: 5487 | B68: BR05 | C68: 2024-09-07 | D68: S004 | E68: Personal Care | F68: Shampoo | G68: 2 | H68: ₦24,278.80 | I68: None | J68: cash | K68: NEW | M68: no
A69: 5297 | B69: BR01 | C69: 7/10/2024 | D69: S006 | E69: Electronics | F69: HDMI Cable | G69: 1 | H69: 42864.9 | J69: cash | K69: NEW | M69: No
A70: 5199 | B70: BR01 | C70: 8/28/2024 | D70: S001 | E70: Electronics | F70: Bluetooth Speaker | G70: 3 | H70: 30975.87 | I70: 15% | J70: Card | K70: Returning | M70: N
A71: 5009 | B71: BR02 | C71: August 13, 2024 | D71: S001 | E71: Home & Kitchen | F71: Kettle | G71: 4 | H71: N/A | I71: 10% | J71: Cash | K71: New | M71: yes
A72: 5389 | B72: BR04 | C72: 5/28/2024 | D72: S007 | E72: Groceries | F72: Sugar (1kg) | G72: 3 | H72: 18262.87 | I72: N/A | J72: Transfer | K72: new
A73: 5430 | B73: BR01 | C73: June 3, 2024 | D73: S006 | E73: Groceries | F73: Rice (5kg) | G73: 2 | H73: N/A | J73: Cash | K73: Returning | M73: no
A74: 5339 | B74: br05 | C74: 1/30/2024 | D74: S006 | E74: Groceries | F74: Spaghetti Pack | G74: 3 | H74: N/A | I74: 10% | J74: CARD | K74: New | M74: Yes
A75: 5470 | B75: BR01 | C75: 2024-05-27 | D75: S003 | E75: Electronics | F75: Power Bank | H75: 32283.11 | J75: Card | K75: Returning | M75: Yes
A76: 5048 | B76: BR03 | C76: 24-Apr-24 | D76: S008 | E76: Groceries | F76: Spaghetti Pack | G76: 2 | H76: 10770.99 | I76: 10% | J76: transfer | K76: returning | M76: yes
A77: 5443 | B77: br03 | C77: 5/19/2024 | D77: S002 | E77: Home & Kitchen | F77: Blender | G77: 5 | H77: 13,720.04 | J77: CASH | K77: NEW | M77: No
A78: 5303 | B78: BR04 | C78: August 9, 2024 | D78: S007 | E78: Electronics | F78: Power Bank | G78: 5 | H78: 35,604.67 | J78: Card | K78: new | M78: No
A79: 5494 | B79: BR01 | C79: 2024-02-17 | D79: S006 | E79: Electronics | F79: Wireless Earbuds | G79: 2 | H79: N/A | I79: N/A | J79: transfer | K79: Returning | M79: No
A80: 5057 | B80: BR03 | C80: 28/4/2024 | D80: S003 | E80: Groceries | F80: Cooking Oil (1L) | G80: 5 | H80: N/A | I80: 0% | J80: Cash | K80: returning | M80: Y
A81: 5070 | B81: br01 | C81: 2024-03-15 | D81: S008 | E81: Electronics | F81: HDMI Cable | H81: 38618.67 | I81: 0% | J81: Transfer | K81: NEW | M81: Y
A82: 5078 | B82: BR02 | C82: 14-Jan-24 | D82: S006 | E82: Groceries | F82: Tomato Paste | G82: 2 | H82: N/A | I82: 15% | J82: Card | K82: RETURNING | M82: Yes
A83: 5106 | B83: BR02 | C83: 21/4/2024 | D83: S002 | E83: Electronics | F83: Bluetooth Speaker | G83: 2 | H83: ₦28,396.83 | I83: None | J83: card | K83: Returning | M83: Yes
A84: 5437 | B84: BR01 | C84: 18-Jan-24 | D84: S003 | E84: Personal Care | F84: Shampoo | G84: 5 | H84: 1,342.23 | I84: None | J84: Card | K84: NEW
A85: 5442 | B85: BR01 | C85: 23-Jun-24 | D85: S003 | E85: Personal Care | F85: Soap Bar | H85: 26,565.69 | I85: 15% | J85: Card | K85: Returning
A86: 5341 | B86: BR01 | C86: 6-Jul-24 | D86: S001 | E86: Electronics | F86: Wireless Earbuds | G86: 2 | H86: 2892.21 | I86: 0% | J86: CARD | K86: RETURNING
A87: 5413 | B87: BR01 | C87: 3/9/2024 | D87: S005 | E87: Personal Care | F87: Deodorant | G87: 3 | H87: N/A | I87: None | J87: CASH | K87: Returning
A88: 5147 | B88: br03 | C88: 23-Jan-24 | D88: S005 | E88: Electronics | F88: Phone Charger | G88: 2 | H88: ₦20,517.81 | I88: 5% | J88: Transfer | K88: returning
A89: 5480 | B89: BR03 | C89: 29-Feb-24 | D89: S002 | E89: Groceries | F89: Tomato Paste | G89: 2 | H89: N/A | I89: 0% | J89: Cash | K89: NEW | M89: no
A90: 5500 | B90: BR04 | C90: 2024-06-02 | D90: S006 | E90: Personal Care | F90: Toothpaste | H90: ₦42,248.05 | I90: N/A | J90: Card | K90: New
A91: 5096 | B91: BR03 | C91: 2/21/2024 | D91: S006 | E91: Groceries | F91: Sugar (1kg) | H91: 26,419.26 | I91: 10% | J91: cash | K91: NEW | M91: Y
A92: 5279 | B92: BR01 | C92: August 16, 2024 | D92: S002 | E92: Personal Care | F92: Toothpaste | G92: 4 | H92: 3763.73 | J92: Card | K92: returning | M92: Yes
A93: 5093 | B93: BR04 | C93: 19-Jul-24 | D93: S002 | E93: Home & Kitchen | F93: Storage Containers | H93: 16,169.56 | I93: 0% | J93: Transfer | K93: returning | M93: yes
A94: 5030 | B94: BR02 | C94: 29/4/2024 | D94: S001 | E94: Electronics | F94: HDMI Cable | G94: 2 | H94: N/A | I94: 10% | J94: cash | K94: NEW | M94: N
A95: 5436 | B95: BR04 | C95: 4/21/2024 | D95: S003 | E95: Electronics | F95: Phone Charger | H95: ₦18,697.12 | I95: N/A | J95: Cash | K95: Returning | M95: No
A96: 5432 | B96: BR05 | C96: 3/8/2024 | D96: S001 | E96: Personal Care | F96: Soap Bar | H96: ₦26,200.63 | I96: 5% | J96: CASH | K96: Returning | M96: N
A97: 5098 | B97: BR02 | C97: 14-Mar-24 | D97: S008 | E97: Electronics | F97: Phone Charger | G97: 4 | H97: N/A | I97: N/A | J97: Card | K97: Returning | M97: no
A98: 5146 | B98: BR02 | C98: June 14, 2024 | D98: S002 | E98: Electronics | F98: Wireless Earbuds | G98: 5 | H98: N/A | J98: Card | K98: RETURNING | M98: Yes
A99: 5411 | B99: BR05 | C99: 9/2/2024 | D99: S001 | E99: Groceries | F99: Rice (5kg) | G99: 1 | H99: 40070.51 | I99: 15% | J99: Card | K99: Returning | M99: Y
A100: 5183 | B100: br02 | C100: 3/7/2024 | D100: S001 | E100: Groceries | F100: Rice (5kg) | G100: 2 | H100: ₦40,231.34 | I100: 5% | J100: Cash | K100: RETURNING | M100: Yes
...

Sheet Cleaned_Transactions
A1: Transaction_Id | B1: Branch_Code | C1: Branch_Name | D1: Date_of_Sale | E1: Staff_Id | F1: Staff_Name | G1: Product_Category | H1: Product_Name | I1: Quantity | J1: Unit_Price | K1: Discount_Applied | L1: Payment_Method | M1: Customer_Type | N1: Total_Sale | O1: Returned
A2: 5453 | B2: BR02 | C2: =IFERROR(VLOOKUP(B2,Branches!A:B, 2, FALSE), B2&"(NOT FOUND)") -> Wuse Branch | D2: 45315 | E2: S006 | F2: =IFERROR(VLOOKUP(E2, Staff!A:B, 2, FALSE), E2&" (NOT FOUND)") -> Ibrahim Sani | G2: Electronics | H2: Bluetooth Speaker | I2: 5 | K2: 0 | L2: Card | M2: Returning | N2: =IF(OR(I2="",J2=""),"",IF(OR(K2="", K2=0), I2*J2, (I2*J2)-(K2/100)*I2*J2)) | O2: NO
A3: 5302 | B3: BR01 | C3: =IFERROR(VLOOKUP(B3,Branches!A:B, 2, FALSE), B3&"(NOT FOUND)") -> Lekki Branch | D3: 45309 | E3: S002 | F3: =IFERROR(VLOOKUP(E3, Staff!A:B, 2, FALSE), E3&" (NOT FOUND)") -> Tobi Adewale | G3: Home & Kitchen | H3: Storage Containers | J3: 10605.57 | L3: Card | M3: Returning | N3: =IF(OR(I3="",J3=""),"",IF(OR(K3="", K3=0), I3*J3, (I3*J3)-(K3/100)*I3*J3)) | O3: YES
A4: 5026 | B4: BR02 | C4: =IFERROR(VLOOKUP(B4,Branches!A:B, 2, FALSE), B4&"(NOT FOUND)") -> Wuse Branch | D4: 45550 | E4: S005 | F4: =IFERROR(VLOOKUP(E4, Staff!A:B, 2, FALSE), E4&" (NOT FOUND)") -> Funke Ajayi | G4: Groceries | H4: Spaghetti Pack | J4: 8416.54 | K4: 0 | L4: Card | M4: New | N4: =IF(OR(I4="",J4=""),"",IF(OR(K4="", K4=0), I4*J4, (I4*J4)-(K4/100)*I4*J4)) | O4: YES
A5: 5001 | B5: BR02 | C5: =IFERROR(VLOOKUP(B5,Branches!A:B, 2, FALSE), B5&"(NOT FOUND)") -> Wuse Branch | D5: 45509 | E5: S002 | F5: =IFERROR(VLOOKUP(E5, Staff!A:B, 2, FALSE), E5&" (NOT FOUND)") -> Tobi Adewale | G5: Electronics | H5: HDMI Cable | I5: 5 | K5: 15 | L5: Card | M5: New | N5: =IF(OR(I5="",J5=""),"",IF(OR(K5="", K5=0), I5*J5, (I5*J5)-(K5/100)*I5*J5)) | O5: YES
A6: 5380 | B6: BR01 | C6: =IFERROR(VLOOKUP(B6,Branches!A:B, 2, FALSE), B6&"(NOT FOUND)") -> Lekki Branch | D6: 45434 | E6: S002 | F6: =IFERROR(VLOOKUP(E6, Staff!A:B, 2, FALSE), E6&" (NOT FOUND)") -> Tobi Adewale | G6: Home & Kitchen | H6: Blender | I6: 1 | L6: Cash | M6: Returning | N6: =IF(OR(I6="",J6=""),"",IF(OR(K6="", K6=0), I6*J6, (I6*J6)-(K6/100)*I6*J6)) | Q6: =IFERROR(VALUE(SUBSTITUTE(#REF!,"₦","")), "")
A7: 5214 | B7: BRXX | C7: =IFERROR(VLOOKUP(B7,Branches!A:B, 2, FALSE), B7&"(NOT FOUND)") -> BRXX(NOT FOUND) | D7: 45530 | E7: S003 | F7: =IFERROR(VLOOKUP(E7, Staff!A:B, 2, FALSE), E7&" (NOT FOUND)") -> Halima Yusuf | G7: Home & Kitchen | H7: Cutlery Set | J7: 33815.79 | K7: 5 | L7: Cash | M7: Returning | N7: =IF(OR(I7="",J7=""),"",IF(OR(K7="", K7=0), I7*J7, (I7*J7)-(K7/100)*I7*J7)) | O7: YES
A8: 5410 | B8: BR04 | C8: =IFERROR(VLOOKUP(B8,Branches!A:B, 2, FALSE), B8&"(NOT FOUND)") -> Sabon Gari Branch | D8: 45520 | E8: S007 | F8: =IFERROR(VLOOKUP(E8, Staff!A:B, 2, FALSE), E8&" (NOT FOUND)") -> Kelechi Umeh | G8: Groceries | H8: Cooking Oil (1L) | I8: 5 | J8: 23072.48 | K8: 0 | L8: Transfer | M8: New | N8: =IF(OR(I8="",J8=""),"",IF(OR(K8="", K8=0), I8*J8, (I8*J8)-(K8/100)*I8*J8)) -> 115362.4 | O8: NO | Q8: =IFERROR(VALUE(SUBSTITUTE(#REF!,"₦","")), "")
A9: 5350 | B9: BR01 | C9: =IFERROR(VLOOKUP(B9,Branches!A:B, 2, FALSE), B9&"(NOT FOUND)") -> Lekki Branch | D9: 45415 | E9: S006 | F9: =IFERROR(VLOOKUP(E9, Staff!A:B, 2, FALSE), E9&" (NOT FOUND)") -> Ibrahim Sani | G9: Personal Care | H9: Toothpaste | I9: 5 | J9: 32386.21 | K9: 0 | L9: Card | M9: New | N9: =IF(OR(I9="",J9=""),"",IF(OR(K9="", K9=0), I9*J9, (I9*J9)-(K9/100)*I9*J9)) -> 161931.05 | O9: NO | Q9: =IFERROR(VALUE(SUBSTITUTE(#REF!,"₦","")), "")
A10: 5445 | B10: BR05 | C10: =IFERROR(VLOOKUP(B10,Branches!A:B, 2, FALSE), B10&"(NOT FOUND)") -> Bodija Branch | D10: 45357 | E10: S007 | F10: =IFERROR(VLOOKUP(E10, Staff!A:B, 2, FALSE), E10&" (NOT FOUND)") -> Kelechi Umeh | G10: Home & Kitchen | H10: Cutlery Set | I10: 1 | J10: 1321.59 | K10: 10 | L10: Card | M10: Returning | N10: =IF(OR(I10="",J10=""),"",IF(OR(K10="", K10=0), I10*J10, (I10*J10)-(K10/100)*I10*J10)) -> 1189.431 | O10: YES
A11: 5227 | B11: BR05 | C11: =IFERROR(VLOOKUP(B11,Branches!A:B, 2, FALSE), B11&"(NOT FOUND)") -> Bodija Branch | D11: 45447 | E11: S001 | F11: =IFERROR(VLOOKUP(E11, Staff!A:B, 2, FALSE), E11&" (NOT FOUND)") -> Chika Nwankwo | G11: Personal Care | H11: Deodorant | L11: Transfer | M11: New | N11: =IF(OR(I11="",J11=""),"",IF(OR(K11="", K11=0), I11*J11, (I11*J11)-(K11/100)*I11*J11)) | O11: NO
A12: 5478 | B12: BR03 | C12: =IFERROR(VLOOKUP(B12,Branches!A:B, 2, FALSE), B12&"(NOT FOUND)") -> GRA Branch | D12: 45397 | E12: S003 | F12: =IFERROR(VLOOKUP(E12, Staff!A:B, 2, FALSE), E12&" (NOT FOUND)") -> Halima Yusuf | G12: Electronics | H12: Phone Charger | J12: 26958.25 | K12: 10 | L12: Transfer | M12: Returning | N12: =IF(OR(I12="",J12=""),"",IF(OR(K12="", K12=0), I12*J12, (I12*J12)-(K12/100)*I12*J12)) | O12: NO
A13: 5439 | B13: BR02 | C13: =IFERROR(VLOOKUP(B13,Branches!A:B, 2, FALSE), B13&"(NOT FOUND)") -> Wuse Branch | D13: 45420 | E13: S004 | F13: =IFERROR(VLOOKUP(E13, Staff!A:B, 2, FALSE), E13&" (NOT FOUND)") -> Ekene Obi | G13: Personal Care | H13: Toothpaste | I13: 3 | K13: 5 | L13: Cash | M13: New | N13: =IF(OR(I13="",J13=""),"",IF(OR(K13="", K13=0), I13*J13, (I13*J13)-(K13/100)*I13*J13)) | O13: NO
A14: 5058 | B14: BR01 | C14: =IFERROR(VLOOKUP(B14,Branches!A:B, 2, FALSE), B14&"(NOT FOUND)") -> Lekki Branch | D14: 45554 | E14: S099 | F14: =IFERROR(VLOOKUP(E14, Staff!A:B, 2, FALSE), E14&" (NOT FOUND)") -> S099 (NOT FOUND) | G14: Home & Kitchen | H14: Blender | I14: 3 | L14: Cash | M14: New | N14: =IF(OR(I14="",J14=""),"",IF(OR(K14="", K14=0), I14*J14, (I14*J14)-(K14/100)*I14*J14)) | O14: NO
A15: 5384 | B15: BR05 | C15: =IFERROR(VLOOKUP(B15,Branches!A:B, 2, FALSE), B15&"(NOT FOUND)") -> Bodija Branch | D15: 45388 | E15: S004 | F15: =IFERROR(VLOOKUP(E15, Staff!A:B, 2, FALSE), E15&" (NOT FOUND)") -> Ekene Obi | G15: Home & Kitchen | H15: Storage Containers | I15: 2 | J15: 17169.84 | K15: 15 | L15: Transfer | M15: Returning | N15: =IF(OR(I15="",J15=""),"",IF(OR(K15="", K15=0), I15*J15, (I15*J15)-(K15/100)*I15*J15)) -> 29188.728 | O15: NO
A16: 5101 | B16: BR05 | C16: =IFERROR(VLOOKUP(B16,Branches!A:B, 2, FALSE), B16&"(NOT FOUND)") -> Bodija Branch | D16: 45549 | E16: S004 | F16: =IFERROR(VLOOKUP(E16, Staff!A:B, 2, FALSE), E16&" (NOT FOUND)") -> Ekene Obi | G16: Personal Care | H16: Deodorant | I16: 3 | J16: 25154.23 | K16: 0 | L16: Transfer | M16: Returning | N16: =IF(OR(I16="",J16=""),"",IF(OR(K16="", K16=0), I16*J16, (I16*J16)-(K16/100)*I16*J16)) -> 75462.69 | O16: NO
A17: 5176 | B17: BR03 | C17: =IFERROR(VLOOKUP(B17,Branches!A:B, 2, FALSE), B17&"(NOT FOUND)") -> GRA Branch | D17: 45373 | E17: S100 | F17: =IFERROR(VLOOKUP(E17, Staff!A:B, 2, FALSE), E17&" (NOT FOUND)") -> S100 (NOT FOUND) | G17: Groceries | H17: Tomato Paste | I17: 1 | K17: 5 | L17: Transfer | M17: Returning | N17: =IF(OR(I17="",J17=""),"",IF(OR(K17="", K17=0), I17*J17, (I17*J17)-(K17/100)*I17*J17)) | O17: NO
A18: 5310 | B18: BR04 | C18: =IFERROR(VLOOKUP(B18,Branches!A:B, 2, FALSE), B18&"(NOT FOUND)") -> Sabon Gari Branch | D18: 45463 | E18: S003 | F18: =IFERROR(VLOOKUP(E18, Staff!A:B, 2, FALSE), E18&" (NOT FOUND)") -> Halima Yusuf | G18: Groceries | H18: Cooking Oil (1L) | K18: 10 | L18: Cash | M18: Returning | N18: =IF(OR(I18="",J18=""),"",IF(OR(K18="", K18=0), I18*J18, (I18*J18)-(K18/100)*I18*J18)) | O18: NO
A19: 5167 | B19: BR03 | C19: =IFERROR(VLOOKUP(B19,Branches!A:B, 2, FALSE), B19&"(NOT FOUND)") -> GRA Branch | D19: 45382 | E19: S007 | F19: =IFERROR(VLOOKUP(E19, Staff!A:B, 2, FALSE), E19&" (NOT FOUND)") -> Kelechi Umeh | G19: Groceries | H19: Spaghetti Pack | I19: 1 | J19: 23400.68 | K19: 10 | L19: Transfer | M19: New | N19: =IF(OR(I19="",J19=""),"",IF(OR(K19="", K19=0), I19*J19, (I19*J19)-(K19/100)*I19*J19)) -> 21060.612 | O19: NO
A20: 5217 | B20: BR05 | C20: =IFERROR(VLOOKUP(B20,Branches!A:B, 2, FALSE), B20&"(NOT FOUND)") -> Bodija Branch | D20: 45561 | E20: S003 | F20: =IFERROR(VLOOKUP(E20, Staff!A:B, 2, FALSE), E20&" (NOT FOUND)") -> Halima Yusuf | G20: Groceries | H20: Tomato Paste | I20: 4 | J20: 5589.59 | L20: Cash | M20: Returning | N20: =IF(OR(I20="",J20=""),"",IF(OR(K20="", K20=0), I20*J20, (I20*J20)-(K20/100)*I20*J20)) -> 22358.36 | O20: YES
A21: 5007 | B21: BR02 | C21: =IFERROR(VLOOKUP(B21,Branches!A:B, 2, FALSE), B21&"(NOT FOUND)") -> Wuse Branch | D21: 45504 | E21: S008 | F21: =IFERROR(VLOOKUP(E21, Staff!A:B, 2, FALSE), E21&" (NOT FOUND)") -> Ronke Bakare | G21: Electronics | H21: Power Bank | I21: 5 | L21: Card | M21: New | N21: =IF(OR(I21="",J21=""),"",IF(OR(K21="", K21=0), I21*J21, (I21*J21)-(K21/100)*I21*J21)) | O21: NO
A22: 5363 | B22: BR05 | C22: =IFERROR(VLOOKUP(B22,Branches!A:B, 2, FALSE), B22&"(NOT FOUND)") -> Bodija Branch | D22: 45553 | E22: S003 | F22: =IFERROR(VLOOKUP(E22, Staff!A:B, 2, FALSE), E22&" (NOT FOUND)") -> Halima Yusuf | G22: Home & Kitchen | H22: Kettle | I22: 4 | J22: 37413.7 | K22: 0 | L22: Cash | M22: Returning | N22: =IF(OR(I22="",J22=""),"",IF(OR(K22="", K22=0), I22*J22, (I22*J22)-(K22/100)*I22*J22)) -> 149654.8
A23: 5271 | B23: BR03 | C23: =IFERROR(VLOOKUP(B23,Branches!A:B, 2, FALSE), B23&"(NOT FOUND)") -> GRA Branch | D23: 45320 | E23: S004 | F23: =IFERROR(VLOOKUP(E23, Staff!A:B, 2, FALSE), E23&" (NOT FOUND)") -> Ekene Obi | G23: Personal Care | H23: Soap Bar | I23: 5 | K23: 10 | L23: Card | M23: Returning | N23: =IF(OR(I23="",J23=""),"",IF(OR(K23="", K23=0), I23*J23, (I23*J23)-(K23/100)*I23*J23)) | O23: YES
A24: 5235 | B24: BR03 | C24: =IFERROR(VLOOKUP(B24,Branches!A:B, 2, FALSE), B24&"(NOT FOUND)") -> GRA Branch | D24: 45380 | E24: S008 | F24: =IFERROR(VLOOKUP(E24, Staff!A:B, 2, FALSE), E24&" (NOT FOUND)") -> Ronke Bakare | G24: Electronics | H24: HDMI Cable | I24: 1 | J24: 42907.41 | K24: 5 | L24: Card | M24: New | N24: =IF(OR(I24="",J24=""),"",IF(OR(K24="", K24=0), I24*J24, (I24*J24)-(K24/100)*I24*J24)) -> 40762.04 | O24: NO
A25: 5116 | B25: BR02 | C25: =IFERROR(VLOOKUP(B25,Branches!A:B, 2, FALSE), B25&"(NOT FOUND)") -> Wuse Branch | D25: 45495 | E25: S006 | F25: =IFERROR(VLOOKUP(E25, Staff!A:B, 2, FALSE), E25&" (NOT FOUND)") -> Ibrahim Sani | G25: Groceries | H25: Cooking Oil (1L) | I25: 1 | K25: 15 | L25: Card | M25: Returning | N25: =IF(OR(I25="",J25=""),"",IF(OR(K25="", K25=0), I25*J25, (I25*J25)-(K25/100)*I25*J25)) | O25: YES
A26: 5353 | B26: BR05 | C26: =IFERROR(VLOOKUP(B26,Branches!A:B, 2, FALSE), B26&"(NOT FOUND)") -> Bodija Branch | D26: 45400 | E26: S008 | F26: =IFERROR(VLOOKUP(E26, Staff!A:B, 2, FALSE), E26&" (NOT FOUND)") -> Ronke Bakare | G26: Home & Kitchen | H26: Cutlery Set | I26: 1 | K26: 10 | L26: Cash | M26: Returning | N26: =IF(OR(I26="",J26=""),"",IF(OR(K26="", K26=0), I26*J26, (I26*J26)-(K26/100)*I26*J26))
A27: 5338 | B27: BR05 | C27: =IFERROR(VLOOKUP(B27,Branches!A:B, 2, FALSE), B27&"(NOT FOUND)") -> Bodija Branch | D27: 45343 | E27: S003 | F27: =IFERROR(VLOOKUP(E27, Staff!A:B, 2, FALSE), E27&" (NOT FOUND)") -> Halima Yusuf | G27: Groceries | H27: Cooking Oil (1L) | K27: 10 | L27: Cash | M27: Returning | N27: =IF(OR(I27="",J27=""),"",IF(OR(K27="", K27=0), I27*J27, (I27*J27)-(K27/100)*I27*J27)) | O27: NO
A28: 5343 | B28: BR02 | C28: =IFERROR(VLOOKUP(B28,Branches!A:B, 2, FALSE), B28&"(NOT FOUND)") -> Wuse Branch | D28: 45557 | E28: S006 | F28: =IFERROR(VLOOKUP(E28, Staff!A:B, 2, FALSE), E28&" (NOT FOUND)") -> Ibrahim Sani | G28: Electronics | H28: HDMI Cable | I28: 3 | L28: Card | M28: New | N28: =IF(OR(I28="",J28=""),"",IF(OR(K28="", K28=0), I28*J28, (I28*J28)-(K28/100)*I28*J28)) | O28: NO
A29: 5372 | B29: BR01 | C29: =IFERROR(VLOOKUP(B29,Branches!A:B, 2, FALSE), B29&"(NOT FOUND)") -> Lekki Branch | D29: 45528 | E29: S008 | F29: =IFERROR(VLOOKUP(E29, Staff!A:B, 2, FALSE), E29&" (NOT FOUND)") -> Ronke Bakare | G29: Home & Kitchen | H29: Kettle | I29: 4 | K29: 5 | L29: Card | M29: Returning | N29: =IF(OR(I29="",J29=""),"",IF(OR(K29="", K29=0), I29*J29, (I29*J29)-(K29/100)*I29*J29)) | O29: YES
A30: 5224 | B30: BR01 | C30: =IFERROR(VLOOKUP(B30,Branches!A:B, 2, FALSE), B30&"(NOT FOUND)") -> Lekki Branch | D30: 45323 | E30: S002 | F30: =IFERROR(VLOOKUP(E30, Staff!A:B, 2, FALSE), E30&" (NOT FOUND)") -> Tobi Adewale | G30: Personal Care | H30: Soap Bar | I30: 1 | J30: 30043.06 | L30: Card | M30: Returning | N30: =IF(OR(I30="",J30=""),"",IF(OR(K30="", K30=0), I30*J30, (I30*J30)-(K30/100)*I30*J30)) -> 30043.06
A31: 5205 | B31: BR04 | C31: =IFERROR(VLOOKUP(B31,Branches!A:B, 2, FALSE), B31&"(NOT FOUND)") -> Sabon Gari Branch | D31: 45313 | E31: S008 | F31: =IFERROR(VLOOKUP(E31, Staff!A:B, 2, FALSE), E31&" (NOT FOUND)") -> Ronke Bakare | G31: Electronics | H31: Power Bank | I31: 3 | J31: 27994.84 | L31: Transfer | M31: Returning | N31: =IF(OR(I31="",J31=""),"",IF(OR(K31="", K31=0), I31*J31, (I31*J31)-(K31/100)*I31*J31)) -> 83984.52 | O31: NO
A32: 5305 | B32: BRXX | C32: =IFERROR(VLOOKUP(B32,Branches!A:B, 2, FALSE), B32&"(NOT FOUND)") -> BRXX(NOT FOUND) | D32: 45401 | E32: S002 | F32: =IFERROR(VLOOKUP(E32, Staff!A:B, 2, FALSE), E32&" (NOT FOUND)") -> Tobi Adewale | G32: Personal Care | H32: Shampoo | I32: 2 | J32: 22968.48 | L32: Transfer | M32: New | N32: =IF(OR(I32="",J32=""),"",IF(OR(K32="", K32=0), I32*J32, (I32*J32)-(K32/100)*I32*J32)) -> 45936.96 | O32: YES
A33: 5210 | B33: BR02 | C33: =IFERROR(VLOOKUP(B33,Branches!A:B, 2, FALSE), B33&"(NOT FOUND)") -> Wuse Branch | D33: 45318 | E33: S001 | F33: =IFERROR(VLOOKUP(E33, Staff!A:B, 2, FALSE), E33&" (NOT FOUND)") -> Chika Nwankwo | G33: Groceries | H33: Sugar (1kg) | I33: 3 | J33: 4354.34 | L33: Transfer | M33: Returning | N33: =IF(OR(I33="",J33=""),"",IF(OR(K33="", K33=0), I33*J33, (I33*J33)-(K33/100)*I33*J33)) -> 13063.02 | O33: NO
A34: 5008 | B34: BR04 | C34: =IFERROR(VLOOKUP(B34,Branches!A:B, 2, FALSE), B34&"(NOT FOUND)") -> Sabon Gari Branch | D34: 45511 | E34: S003 | F34: =IFERROR(VLOOKUP(E34, Staff!A:B, 2, FALSE), E34&" (NOT FOUND)") -> Halima Yusuf | G34: Groceries | H34: Cooking Oil (1L) | I34: 1 | J34: 22080.84 | K34: 0 | L34: Card | M34: New | N34: =IF(OR(I34="",J34=""),"",IF(OR(K34="", K34=0), I34*J34, (I34*J34)-(K34/100)*I34*J34)) -> 22080.84 | O34: NO
A35: 5355 | B35: BR05 | C35: =IFERROR(VLOOKUP(B35,Branches!A:B, 2, FALSE), B35&"(NOT FOUND)") -> Bodija Branch | D35: 45450 | E35: S007 | F35: =IFERROR(VLOOKUP(E35, Staff!A:B, 2, FALSE), E35&" (NOT FOUND)") -> Kelechi Umeh | G35: Personal Care | H35: Body Lotion | I35: 5 | J35: 25569.2 | L35: Cash | M35: Returning | N35: =IF(OR(I35="",J35=""),"",IF(OR(K35="", K35=0), I35*J35, (I35*J35)-(K35/100)*I35*J35)) -> 127846 | O35: YES
A36: 5431 | B36: BR05 | C36: =IFERROR(VLOOKUP(B36,Branches!A:B, 2, FALSE), B36&"(NOT FOUND)") -> Bodija Branch | D36: 45352 | E36: S003 | F36: =IFERROR(VLOOKUP(E36, Staff!A:B, 2, FALSE), E36&" (NOT FOUND)") -> Halima Yusuf | G36: Electronics | H36: HDMI Cable | I36: 2 | J36: 36302.69 | L36: Cash | M36: Returning | N36: =IF(OR(I36="",J36=""),"",IF(OR(K36="", K36=0), I36*J36, (I36*J36)-(K36/100)*I36*J36)) -> 72605.38 | O36: YES
A37: 5373 | B37: BR05 | C37: =IFERROR(VLOOKUP(B37,Branches!A:B, 2, FALSE), B37&"(NOT FOUND)") -> Bodija Branch | D37: 45359 | E37: S002 | F37: =IFERROR(VLOOKUP(E37, Staff!A:B, 2, FALSE), E37&" (NOT FOUND)") -> Tobi Adewale | G37: Personal Care | H37: Deodorant | I37: 1 | J37: 12020.08 | L37: Cash | M37: Returning | N37: =IF(OR(I37="",J37=""),"",IF(OR(K37="", K37=0), I37*J37, (I37*J37)-(K37/100)*I37*J37)) -> 12020.08
A38: 5402 | B38: BR05 | C38: =IFERROR(VLOOKUP(B38,Branches!A:B, 2, FALSE), B38&"(NOT FOUND)") -> Bodija Branch | D38: 45342 | E38: S006 | F38: =IFERROR(VLOOKUP(E38, Staff!A:B, 2, FALSE), E38&" (NOT FOUND)") -> Ibrahim Sani | G38: Groceries | H38: Cooking Oil (1L) | I38: 1 | J38: 30457.19 | L38: Card | M38: New | N38: =IF(OR(I38="",J38=""),"",IF(OR(K38="", K38=0), I38*J38, (I38*J38)-(K38/100)*I38*J38)) -> 30457.19 | O38: NO
A39: 5394 | B39: BR09 | C39: =IFERROR(VLOOKUP(B39,Branches!A:B, 2, FALSE), B39&"(NOT FOUND)") -> BR09(NOT FOUND) | D39: 45325 | E39: S008 | F39: =IFERROR(VLOOKUP(E39, Staff!A:B, 2, FALSE), E39&" (NOT FOUND)") -> Ronke Bakare | G39: Home & Kitchen | H39: Blender | I39: 5 | L39: Cash | M39: Returning | N39: =IF(OR(I39="",J39=""),"",IF(OR(K39="", K39=0), I39*J39, (I39*J39)-(K39/100)*I39*J39)) | O39: YES
A40: 5103 | B40: BR04 | C40: =IFERROR(VLOOKUP(B40,Branches!A:B, 2, FALSE), B40&"(NOT FOUND)") -> Sabon Gari Branch | D40: 45334 | E40: S001 | F40: =IFERROR(VLOOKUP(E40, Staff!A:B, 2, FALSE), E40&" (NOT FOUND)") -> Chika Nwankwo | G40: Groceries | H40: Tomato Paste | L40: Card | M40: Returning | N40: =IF(OR(I40="",J40=""),"",IF(OR(K40="", K40=0), I40*J40, (I40*J40)-(K40/100)*I40*J40)) | O40: NO
A41: 5227 | B41: BR05 | C41: =IFERROR(VLOOKUP(B41,Branches!A:B, 2, FALSE), B41&"(NOT FOUND)") -> Bodija Branch | D41: 45447 | E41: S001 | F41: =IFERROR(VLOOKUP(E41, Staff!A:B, 2, FALSE), E41&" (NOT FOUND)") -> Chika Nwankwo | G41: Personal Care | H41: Deodorant | L41: Transfer | M41: New | N41: =IF(OR(I41="",J41=""),"",IF(OR(K41="", K41=0), I41*J41, (I41*J41)-(K41/100)*I41*J41)) | O41: NO
A42: 5164 | B42: BR03 | C42: =IFERROR(VLOOKUP(B42,Branches!A:B, 2, FALSE), B42&"(NOT FOUND)") -> GRA Branch | D42: 45561 | E42: S005 | F42: =IFERROR(VLOOKUP(E42, Staff!A:B, 2, FALSE), E42&" (NOT FOUND)") -> Funke Ajayi | G42: Groceries | H42: Rice (5kg) | I42: 1 | J42: 1625.54 | K42: 0 | L42: Cash | M42: New | N42: =IF(OR(I42="",J42=""),"",IF(OR(K42="", K42=0), I42*J42, (I42*J42)-(K42/100)*I42*J42)) -> 1625.54 | O42: NO
A43: 5171 | B43: BR04 | C43: =IFERROR(VLOOKUP(B43,Branches!A:B, 2, FALSE), B43&"(NOT FOUND)") -> Sabon Gari Branch | D43: 45549 | E43: S004 | F43: =IFERROR(VLOOKUP(E43, Staff!A:B, 2, FALSE), E43&" (NOT FOUND)") -> Ekene Obi | G43: Electronics | H43: Phone Charger | I43: 5 | J43: 4070.17 | L43: Transfer | M43: New | N43: =IF(OR(I43="",J43=""),"",IF(OR(K43="", K43=0), I43*J43, (I43*J43)-(K43/100)*I43*J43)) -> 20350.85
A44: 5319 | B44: BR04 | C44: =IFERROR(VLOOKUP(B44,Branches!A:B, 2, FALSE), B44&"(NOT FOUND)") -> Sabon Gari Branch | D44: 45374 | E44: S001 | F44: =IFERROR(VLOOKUP(E44, Staff!A:B, 2, FALSE), E44&" (NOT FOUND)") -> Chika Nwankwo | G44: Electronics | H44: HDMI Cable | K44: 0 | L44: Transfer | M44: Returning | N44: =IF(OR(I44="",J44=""),"",IF(OR(K44="", K44=0), I44*J44, (I44*J44)-(K44/100)*I44*J44)) | O44: YES
A45: 5258 | B45: BR02 | C45: =IFERROR(VLOOKUP(B45,Branches!A:B, 2, FALSE), B45&"(NOT FOUND)") -> Wuse Branch | D45: 45450 | E45: S002 | F45: =IFERROR(VLOOKUP(E45, Staff!A:B, 2, FALSE), E45&" (NOT FOUND)") -> Tobi Adewale | G45: Personal Care | H45: Shampoo | I45: 2 | J45: 38312.98 | K45: 10 | L45: Cash | M45: New | N45: =IF(OR(I45="",J45=""),"",IF(OR(K45="", K45=0), I45*J45, (I45*J45)-(K45/100)*I45*J45)) -> 68963.364 | O45: NO
A46: 5179 | B46: BR01 | C46: =IFERROR(VLOOKUP(B46,Branches!A:B, 2, FALSE), B46&"(NOT FOUND)") -> Lekki Branch | D46: 45413 | E46: S006 | F46: =IFERROR(VLOOKUP(E46, Staff!A:B, 2, FALSE), E46&" (NOT FOUND)") -> Ibrahim Sani | G46: Groceries | H46: Rice (5kg) | I46: 1 | J46: 39321.03 | K46: 0 | L46: Cash | M46: Returning | N46: =IF(OR(I46="",J46=""),"",IF(OR(K46="", K46=0), I46*J46, (I46*J46)-(K46/100)*I46*J46)) -> 39321.03
A47: 5068 | B47: BR05 | C47: =IFERROR(VLOOKUP(B47,Branches!A:B, 2, FALSE), B47&"(NOT FOUND)") -> Bodija Branch | D47: 45432 | E47: S008 | F47: =IFERROR(VLOOKUP(E47, Staff!A:B, 2, FALSE), E47&" (NOT FOUND)") -> Ronke Bakare | G47: Personal Care | H47: Toothpaste | K47: 0 | L47: Cash | M47: New | N47: =IF(OR(I47="",J47=""),"",IF(OR(K47="", K47=0), I47*J47, (I47*J47)-(K47/100)*I47*J47)) | O47: NO
A48: 5088 | B48: BR02 | C48: =IFERROR(VLOOKUP(B48,Branches!A:B, 2, FALSE), B48&"(NOT FOUND)") -> Wuse Branch | D48: 45515 | E48: S007 | F48: =IFERROR(VLOOKUP(E48, Staff!A:B, 2, FALSE), E48&" (NOT FOUND)") -> Kelechi Umeh | G48: Personal Care | H48: Toothpaste | I48: 1 | K48: 10 | L48: Card | M48: Returning | N48: =IF(OR(I48="",J48=""),"",IF(OR(K48="", K48=0), I48*J48, (I48*J48)-(K48/100)*I48*J48))
A49: 5173 | B49: BR02 | C49: =IFERROR(VLOOKUP(B49,Branches!A:B, 2, FALSE), B49&"(NOT FOUND)") -> Wuse Branch | D49: 45466 | E49: S003 | F49: =IFERROR(VLOOKUP(E49, Staff!A:B, 2, FALSE), E49&" (NOT FOUND)") -> Halima Yusuf | G49: Home & Kitchen | H49: Non-stick Pan | I49: 2 | J49: 25551.69 | K49: 5 | L49: Cash | M49: Returning | N49: =IF(OR(I49="",J49=""),"",IF(OR(K49="", K49=0), I49*J49, (I49*J49)-(K49/100)*I49*J49)) -> 48548.211
A50: 5013 | B50: BR02 | C50: =IFERROR(VLOOKUP(B50,Branches!A:B, 2, FALSE), B50&"(NOT FOUND)") -> Wuse Branch | D50: 45404 | E50: S006 | F50: =IFERROR(VLOOKUP(E50, Staff!A:B, 2, FALSE), E50&" (NOT FOUND)") -> Ibrahim Sani | G50: Electronics | H50: Wireless Earbuds | I50: 4 | J50: 12033.26 | K50: 15 | L50: Cash | M50: New | N50: =IF(OR(I50="",J50=""),"",IF(OR(K50="", K50=0), I50*J50, (I50*J50)-(K50/100)*I50*J50)) -> 40913.084 | O50: YES
A51: 5496 | B51: BR02 | C51: =IFERROR(VLOOKUP(B51,Branches!A:B, 2, FALSE), B51&"(NOT FOUND)") -> Wuse Branch | D51: 45295 | E51: S001 | F51: =IFERROR(VLOOKUP(E51, Staff!A:B, 2, FALSE), E51&" (NOT FOUND)") -> Chika Nwankwo | G51: Electronics | H51: Wireless Earbuds | I51: 3 | J51: 26033.94 | K51: 10 | L51: Cash | M51: New | N51: =IF(OR(I51="",J51=""),"",IF(OR(K51="", K51=0), I51*J51, (I51*J51)-(K51/100)*I51*J51)) -> 70291.638 | O51: YES
A52: 5473 | B52: BR02 | C52: =IFERROR(VLOOKUP(B52,Branches!A:B, 2, FALSE), B52&"(NOT FOUND)") -> Wuse Branch | D52: 45395 | E52: S006 | F52: =IFERROR(VLOOKUP(E52, Staff!A:B, 2, FALSE), E52&" (NOT FOUND)") -> Ibrahim Sani | G52: Home & Kitchen | H52: Non-stick Pan | K52: 5 | L52: Cash | M52: Returning | N52: =IF(OR(I52="",J52=""),"",IF(OR(K52="", K52=0), I52*J52, (I52*J52)-(K52/100)*I52*J52)) | O52: YES
A53: 5208 | B53: BR05 | C53: =IFERROR(VLOOKUP(B53,Branches!A:B, 2, FALSE), B53&"(NOT FOUND)") -> Bodija Branch | D53: 45405 | E53: S004 | F53: =IFERROR(VLOOKUP(E53, Staff!A:B, 2, FALSE), E53&" (NOT FOUND)") -> Ekene Obi | G53: Home & Kitchen | H53: Kettle | L53: Transfer | M53: New | N53: =IF(OR(I53="",J53=""),"",IF(OR(K53="", K53=0), I53*J53, (I53*J53)-(K53/100)*I53*J53)) | O53: YES
A54: 5213 | B54: BR05 | C54: =IFERROR(VLOOKUP(B54,Branches!A:B, 2, FALSE), B54&"(NOT FOUND)") -> Bodija Branch | D54: 45546 | E54: S008 | F54: =IFERROR(VLOOKUP(E54, Staff!A:B, 2, FALSE), E54&" (NOT FOUND)") -> Ronke Bakare | G54: Groceries | H54: Cooking Oil (1L) | I54: 4 | J54: 38686.51 | L54: Card | M54: Returning | N54: =IF(OR(I54="",J54=""),"",IF(OR(K54="", K54=0), I54*J54, (I54*J54)-(K54/100)*I54*J54)) -> 154746.04 | O54: YES
A55: 5109 | B55: BR03 | C55: =IFERROR(VLOOKUP(B55,Branches!A:B, 2, FALSE), B55&"(NOT FOUND)") -> GRA Branch | D55: 45523 | E55: S008 | F55: =IFERROR(VLOOKUP(E55, Staff!A:B, 2, FALSE), E55&" (NOT FOUND)") -> Ronke Bakare | G55: Home & Kitchen | H55: Cutlery Set | I55: 1 | K55: 15 | L55: Transfer | M55: Returning | N55: =IF(OR(I55="",J55=""),"",IF(OR(K55="", K55=0), I55*J55, (I55*J55)-(K55/100)*I55*J55))
A56: 5178 | B56: BR03 | C56: =IFERROR(VLOOKUP(B56,Branches!A:B, 2, FALSE), B56&"(NOT FOUND)") -> GRA Branch | D56: 45365 | E56: S008 | F56: =IFERROR(VLOOKUP(E56, Staff!A:B, 2, FALSE), E56&" (NOT FOUND)") -> Ronke Bakare | G56: Personal Care | H56: Toothpaste | J56: 20943.64 | L56: Card | M56: Returning | N56: =IF(OR(I56="",J56=""),"",IF(OR(K56="", K56=0), I56*J56, (I56*J56)-(K56/100)*I56*J56)) | O56: NO
A57: 5456 | B57: BR01 | C57: =IFERROR(VLOOKUP(B57,Branches!A:B, 2, FALSE), B57&"(NOT FOUND)") -> Lekki Branch | D57: 45457 | E57: S007 | F57: =IFERROR(VLOOKUP(E57, Staff!A:B, 2, FALSE), E57&" (NOT FOUND)") -> Kelechi Umeh | G57: Personal Care | H57: Soap Bar | J57: 8059.7 | K57: 15 | L57: Card | M57: New | N57: =IF(OR(I57="",J57=""),"",IF(OR(K57="", K57=0), I57*J57, (I57*J57)-(K57/100)*I57*J57)) | O57: NO
A58: 5065 | B58: BR02 | C58: =IFERROR(VLOOKUP(B58,Branches!A:B, 2, FALSE), B58&"(NOT FOUND)") -> Wuse Branch | D58: 45419 | E58: S001 | F58: =IFERROR(VLOOKUP(E58, Staff!A:B, 2, FALSE), E58&" (NOT FOUND)") -> Chika Nwankwo | G58: Personal Care | H58: Shampoo | I58: 4 | J58: 24977.31 | L58: Transfer | M58: New | N58: =IF(OR(I58="",J58=""),"",IF(OR(K58="", K58=0), I58*J58, (I58*J58)-(K58/100)*I58*J58)) -> 99909.24 | O58: YES
A59: 5097 | B59: BR02 | C59: =IFERROR(VLOOKUP(B59,Branches!A:B, 2, FALSE), B59&"(NOT FOUND)") -> Wuse Branch | D59: 45444 | E59: S006 | F59: =IFERROR(VLOOKUP(E59, Staff!A:B, 2, FALSE), E59&" (NOT FOUND)") -> Ibrahim Sani | G59: Groceries | H59: Cooking Oil (1L) | I59: 5 | J59: 7972.12 | L59: Card | M59: Returning | N59: =IF(OR(I59="",J59=""),"",IF(OR(K59="", K59=0), I59*J59, (I59*J59)-(K59/100)*I59*J59)) -> 39860.6 | O59: NO
A60: 5375 | B60: BR03 | C60: =IFERROR(VLOOKUP(B60,Branches!A:B, 2, FALSE), B60&"(NOT FOUND)") -> GRA Branch | D60: 45548 | E60: S003 | F60: =IFERROR(VLOOKUP(E60, Staff!A:B, 2, FALSE), E60&" (NOT FOUND)") -> Halima Yusuf | G60: Electronics | H60: Wireless Earbuds | I60: 1 | J60: 44802.54 | L60: Card | M60: Returning | N60: =IF(OR(I60="",J60=""),"",IF(OR(K60="", K60=0), I60*J60, (I60*J60)-(K60/100)*I60*J60)) -> 44802.54 | O60: NO
A61: 5005 | B61: BR02 | C61: =IFERROR(VLOOKUP(B61,Branches!A:B, 2, FALSE), B61&"(NOT FOUND)") -> Wuse Branch | D61: 45325 | E61: S002 | F61: =IFERROR(VLOOKUP(E61, Staff!A:B, 2, FALSE), E61&" (NOT FOUND)") -> Tobi Adewale | G61: Personal Care | H61: Body Lotion | I61: 5 | J61: 22602.03 | L61: Card | M61: New | N61: =IF(OR(I61="",J61=""),"",IF(OR(K61="", K61=0), I61*J61, (I61*J61)-(K61/100)*I61*J61)) -> 113010.15 | O61: NO
A62: 5282 | B62: BR02 | C62: =IFERROR(VLOOKUP(B62,Branches!A:B, 2, FALSE), B62&"(NOT FOUND)") -> Wuse Branch | D62: 45428 | E62: S003 | F62: =IFERROR(VLOOKUP(E62, Staff!A:B, 2, FALSE), E62&" (NOT FOUND)") -> Halima Yusuf | G62: Groceries | H62: Spaghetti Pack | I62: 3 | J62: 17413.92 | K62: 5 | L62: Cash | M62: Returning | N62: =IF(OR(I62="",J62=""),"",IF(OR(K62="", K62=0), I62*J62, (I62*J62)-(K62/100)*I62*J62)) -> 49629.672 | O62: YES
A63: 5056 | B63: BR01 | C63: =IFERROR(VLOOKUP(B63,Branches!A:B, 2, FALSE), B63&"(NOT FOUND)") -> Lekki Branch | D63: 45429 | E63: S008 | F63: =IFERROR(VLOOKUP(E63, Staff!A:B, 2, FALSE), E63&" (NOT FOUND)") -> Ronke Bakare | G63: Groceries | H63: Cooking Oil (1L) | I63: 4 | J63: 28103.69 | L63: Cash | M63: New | N63: =IF(OR(I63="",J63=""),"",IF(OR(K63="", K63=0), I63*J63, (I63*J63)-(K63/100)*I63*J63)) -> 112414.76 | O63: NO
A64: 5189 | B64: BR03 | C64: =IFERROR(VLOOKUP(B64,Branches!A:B, 2, FALSE), B64&"(NOT FOUND)") -> GRA Branch | D64: 45527 | E64: S003 | F64: =IFERROR(VLOOKUP(E64, Staff!A:B, 2, FALSE), E64&" (NOT FOUND)") -> Halima Yusuf | G64: Electronics | H64: HDMI Cable | I64: 2 | J64: 20149.29 | L64: Cash | M64: Returning | N64: =IF(OR(I64="",J64=""),"",IF(OR(K64="", K64=0), I64*J64, (I64*J64)-(K64/100)*I64*J64)) -> 40298.58 | O64: NO
A65: 5464 | B65: BR01 | C65: =IFERROR(VLOOKUP(B65,Branches!A:B, 2, FALSE), B65&"(NOT FOUND)") -> Lekki Branch | D65: 45521 | E65: S002 | F65: =IFERROR(VLOOKUP(E65, Staff!A:B, 2, FALSE), E65&" (NOT FOUND)") -> Tobi Adewale | G65: Personal Care | H65: Deodorant | I65: 4 | L65: Card | M65: New | N65: =IF(OR(I65="",J65=""),"",IF(OR(K65="", K65=0), I65*J65, (I65*J65)-(K65/100)*I65*J65)) | O65: NO
A66: 5121 | B66: BR02 | C66: =IFERROR(VLOOKUP(B66,Branches!A:B, 2, FALSE), B66&"(NOT FOUND)") -> Wuse Branch | D66: 45430 | E66: S001 | F66: =IFERROR(VLOOKUP(E66, Staff!A:B, 2, FALSE), E66&" (NOT FOUND)") -> Chika Nwankwo | G66: Groceries | H66: Tomato Paste | I66: 2 | K66: 15 | L66: Cash | M66: New | N66: =IF(OR(I66="",J66=""),"",IF(OR(K66="", K66=0), I66*J66, (I66*J66)-(K66/100)*I66*J66)) | O66: YES
A67: 5325 | B67: BR03 | C67: =IFERROR(VLOOKUP(B67,Branches!A:B, 2, FALSE), B67&"(NOT FOUND)") -> GRA Branch | D67: 45323 | E67: S003 | F67: =IFERROR(VLOOKUP(E67, Staff!A:B, 2, FALSE), E67&" (NOT FOUND)") -> Halima Yusuf | G67: Electronics | H67: Power Bank | I67: 3 | J67: 15467.23 | K67: 15 | L67: Cash | M67: New | N67: =IF(OR(I67="",J67=""),"",IF(OR(K67="", K67=0), I67*J67, (I67*J67)-(K67/100)*I67*J67)) -> 39441.437 | O67: NO
A68: 5487 | B68: BR05 | C68: =IFERROR(VLOOKUP(B68,Branches!A:B, 2, FALSE), B68&"(NOT FOUND)") -> Bodija Branch | D68: 45542 | E68: S004 | F68: =IFERROR(VLOOKUP(E68, Staff!A:B, 2, FALSE), E68&" (NOT FOUND)") -> Ekene Obi | G68: Personal Care | H68: Shampoo | I68: 2 | J68: 24278.8 | L68: Cash | M68: New | N68: =IF(OR(I68="",J68=""),"",IF(OR(K68="", K68=0), I68*J68, (I68*J68)-(K68/100)*I68*J68)) -> 48557.6 | O68: NO
A69: 5297 | B69: BR01 | C69: =IFERROR(VLOOKUP(B69,Branches!A:B, 2, FALSE), B69&"(NOT FOUND)") -> Lekki Branch | D69: 45572 | E69: S006 | F69: =IFERROR(VLOOKUP(E69, Staff!A:B, 2, FALSE), E69&" (NOT FOUND)") -> Ibrahim Sani | G69: Electronics | H69: HDMI Cable | I69: 1 | J69: 42864.9 | L69: Cash | M69: New | N69: =IF(OR(I69="",J69=""),"",IF(OR(K69="", K69=0), I69*J69, (I69*J69)-(K69/100)*I69*J69)) -> 42864.9 | O69: NO
A70: 5199 | B70: BR01 | C70: =IFERROR(VLOOKUP(B70,Branches!A:B, 2, FALSE), B70&"(NOT FOUND)") -> Lekki Branch | D70: 45532 | E70: S001 | F70: =IFERROR(VLOOKUP(E70, Staff!A:B, 2, FALSE), E70&" (NOT FOUND)") -> Chika Nwankwo | G70: Electronics | H70: Bluetooth Speaker | I70: 3 | J70: 30975.87 | K70: 15 | L70: Card | M70: Returning | N70: =IF(OR(I70="",J70=""),"",IF(OR(K70="", K70=0), I70*J70, (I70*J70)-(K70/100)*I70*J70)) -> 78988.469 | O70: NO
A71: 5009 | B71: BR02 | C71: =IFERROR(VLOOKUP(B71,Branches!A:B, 2, FALSE), B71&"(NOT FOUND)") -> Wuse Branch | D71: 45517 | E71: S001 | F71: =IFERROR(VLOOKUP(E71, Staff!A:B, 2, FALSE), E71&" (NOT FOUND)") -> Chika Nwankwo | G71: Home & Kitchen | H71: Kettle | I71: 4 | K71: 10 | L71: Cash | M71: New | N71: =IF(OR(I71="",J71=""),"",IF(OR(K71="", K71=0), I71*J71, (I71*J71)-(K71/100)*I71*J71)) | O71: YES
A72: 5389 | B72: BR04 | C72: =IFERROR(VLOOKUP(B72,Branches!A:B, 2, FALSE), B72&"(NOT FOUND)") -> Sabon Gari Branch | D72: 45440 | E72: S007 | F72: =IFERROR(VLOOKUP(E72, Staff!A:B, 2, FALSE), E72&" (NOT FOUND)") -> Kelechi Umeh | G72: Groceries | H72: Sugar (1kg) | I72: 3 | J72: 18262.87 | L72: Transfer | M72: New | N72: =IF(OR(I72="",J72=""),"",IF(OR(K72="", K72=0), I72*J72, (I72*J72)-(K72/100)*I72*J72)) -> 54788.61
A73: 5430 | B73: BR01 | C73: =IFERROR(VLOOKUP(B73,Branches!A:B, 2, FALSE), B73&"(NOT FOUND)") -> Lekki Branch | D73: 45446 | E73: S006 | F73: =IFERROR(VLOOKUP(E73, Staff!A:B, 2, FALSE), E73&" (NOT FOUND)") -> Ibrahim Sani | G73: Groceries | H73: Rice (5kg) | I73: 2 | L73: Cash | M73: Returning | N73: =IF(OR(I73="",J73=""),"",IF(OR(K73="", K73=0), I73*J73, (I73*J73)-(K73/100)*I73*J73)) | O73: NO
A74: 5339 | B74: BR05 | C74: =IFERROR(VLOOKUP(B74,Branches!A:B, 2, FALSE), B74&"(NOT FOUND)") -> Bodija Branch | D74: 45321 | E74: S006 | F74: =IFERROR(VLOOKUP(E74, Staff!A:B, 2, FALSE), E74&" (NOT FOUND)") -> Ibrahim Sani | G74: Groceries | H74: Spaghetti Pack | I74: 3 | K74: 10 | L74: Card | M74: New | N74: =IF(OR(I74="",J74=""),"",IF(OR(K74="", K74=0), I74*J74, (I74*J74)-(K74/100)*I74*J74)) | O74: YES
A75: 5470 | B75: BR01 | C75: =IFERROR(VLOOKUP(B75,Branches!A:B, 2, FALSE), B75&"(NOT FOUND)") -> Lekki Branch | D75: 45439 | E75: S003 | F75: =IFERROR(VLOOKUP(E75, Staff!A:B, 2, FALSE), E75&" (NOT FOUND)") -> Halima Yusuf | G75: Electronics | H75: Power Bank | J75: 32283.11 | L75: Card | M75: Returning | N75: =IF(OR(I75="",J75=""),"",IF(OR(K75="", K75=0), I75*J75, (I75*J75)-(K75/100)*I75*J75)) | O75: YES
A76: 5048 | B76: BR03 | C76: =IFERROR(VLOOKUP(B76,Branches!A:B, 2, FALSE), B76&"(NOT FOUND)") -> GRA Branch | D76: 45406 | E76: S008 | F76: =IFERROR(VLOOKUP(E76, Staff!A:B, 2, FALSE), E76&" (NOT FOUND)") -> Ronke Bakare | G76: Groceries | H76: Spaghetti Pack | I76: 2 | J76: 10770.99 | K76: 10 | L76: Transfer | M76: Returning | N76: =IF(OR(I76="",J76=""),"",IF(OR(K76="", K76=0), I76*J76, (I76*J76)-(K76/100)*I76*J76)) -> 19387.782 | O76: YES
A77: 5443 | B77: BR03 | C77: =IFERROR(VLOOKUP(B77,Branches!A:B, 2, FALSE), B77&"(NOT FOUND)") -> GRA Branch | D77: 45431 | E77: S002 | F77: =IFERROR(VLOOKUP(E77, Staff!A:B, 2, FALSE), E77&" (NOT FOUND)") -> Tobi Adewale | G77: Home & Kitchen | H77: Blender | I77: 5 | J77: 13720.04 | L77: Cash | M77: New | N77: =IF(OR(I77="",J77=""),"",IF(OR(K77="", K77=0), I77*J77, (I77*J77)-(K77/100)*I77*J77)) -> 68600.2 | O77: NO
A78: 5303 | B78: BR04 | C78: =IFERROR(VLOOKUP(B78,Branches!A:B, 2, FALSE), B78&"(NOT FOUND)") -> Sabon Gari Branch | D78: 45513 | E78: S007 | F78: =IFERROR(VLOOKUP(E78, Staff!A:B, 2, FALSE), E78&" (NOT FOUND)") -> Kelechi Umeh | G78: Electronics | H78: Power Bank | I78: 5 | J78: 35604.67 | L78: Card | M78: New | N78: =IF(OR(I78="",J78=""),"",IF(OR(K78="", K78=0), I78*J78, (I78*J78)-(K78/100)*I78*J78)) -> 178023.35 | O78: NO
A79: 5494 | B79: BR01 | C79: =IFERROR(VLOOKUP(B79,Branches!A:B, 2, FALSE), B79&"(NOT FOUND)") -> Lekki Branch | D79: 45339 | E79: S006 | F79: =IFERROR(VLOOKUP(E79, Staff!A:B, 2, FALSE), E79&" (NOT FOUND)") -> Ibrahim Sani | G79: Electronics | H79: Wireless Earbuds | I79: 2 | L79: Transfer | M79: Returning | N79: =IF(OR(I79="",J79=""),"",IF(OR(K79="", K79=0), I79*J79, (I79*J79)-(K79/100)*I79*J79)) | O79: NO
A80: 5057 | B80: BR03 | C80: =IFERROR(VLOOKUP(B80,Branches!A:B, 2, FALSE), B80&"(NOT FOUND)") -> GRA Branch | D80: 45410 | E80: S003 | F80: =IFERROR(VLOOKUP(E80, Staff!A:B, 2, FALSE), E80&" (NOT FOUND)") -> Halima Yusuf | G80: Groceries | H80: Cooking Oil (1L) | I80: 5 | K80: 0 | L80: Cash | M80: Returning | N80: =IF(OR(I80="",J80=""),"",IF(OR(K80="", K80=0), I80*J80, (I80*J80)-(K80/100)*I80*J80)) | O80: YES
A81: 5070 | B81: BR01 | C81: =IFERROR(VLOOKUP(B81,Branches!A:B, 2, FALSE), B81&"(NOT FOUND)") -> Lekki Branch | D81: 45366 | E81: S008 | F81: =IFERROR(VLOOKUP(E81, Staff!A:B, 2, FALSE), E81&" (NOT FOUND)") -> Ronke Bakare | G81: Electronics | H81: HDMI Cable | J81: 38618.67 | K81: 0 | L81: Transfer | M81: New | N81: =IF(OR(I81="",J81=""),"",IF(OR(K81="", K81=0), I81*J81, (I81*J81)-(K81/100)*I81*J81)) | O81: YES
A82: 5078 | B82: BR02 | C82: =IFERROR(VLOOKUP(B82,Branches!A:B, 2, FALSE), B82&"(NOT FOUND)") -> Wuse Branch | D82: 45305 | E82: S006 | F82: =IFERROR(VLOOKUP(E82, Staff!A:B, 2, FALSE), E82&" (NOT FOUND)") -> Ibrahim Sani | G82: Groceries | H82: Tomato Paste | I82: 2 | K82: 15 | L82: Card | M82: Returning | N82: =IF(OR(I82="",J82=""),"",IF(OR(K82="", K82=0), I82*J82, (I82*J82)-(K82/100)*I82*J82)) | O82: YES
A83: 5106 | B83: BR02 | C83: =IFERROR(VLOOKUP(B83,Branches!A:B, 2, FALSE), B83&"(NOT FOUND)") -> Wuse Branch | D83: 45403 | E83: S002 | F83: =IFERROR(VLOOKUP(E83, Staff!A:B, 2, FALSE), E83&" (NOT FOUND)") -> Tobi Adewale | G83: Electronics | H83: Bluetooth Speaker | I83: 2 | J83: 28396.83 | L83: Card | M83: Returning | N83: =IF(OR(I83="",J83=""),"",IF(OR(K83="", K83=0), I83*J83, (I83*J83)-(K83/100)*I83*J83)) -> 56793.66 | O83: YES
A84: 5437 | B84: BR01 | C84: =IFERROR(VLOOKUP(B84,Branches!A:B, 2, FALSE), B84&"(NOT FOUND)") -> Lekki Branch | D84: 45309 | E84: S003 | F84: =IFERROR(VLOOKUP(E84, Staff!A:B, 2, FALSE), E84&" (NOT FOUND)") -> Halima Yusuf | G84: Personal Care | H84: Shampoo | I84: 5 | J84: 1342.23 | L84: Card | M84: New | N84: =IF(OR(I84="",J84=""),"",IF(OR(K84="", K84=0), I84*J84, (I84*J84)-(K84/100)*I84*J84)) -> 6711.15
A85: 5442 | B85: BR01 | C85: =IFERROR(VLOOKUP(B85,Branches!A:B, 2, FALSE), B85&"(NOT FOUND)") -> Lekki Branch | D85: 45466 | E85: S003 | F85: =IFERROR(VLOOKUP(E85, Staff!A:B, 2, FALSE), E85&" (NOT FOUND)") -> Halima Yusuf | G85: Personal Care | H85: Soap Bar | J85: 26565.69 | K85: 15 | L85: Card | M85: Returning | N85: =IF(OR(I85="",J85=""),"",IF(OR(K85="", K85=0), I85*J85, (I85*J85)-(K85/100)*I85*J85))
A86: 5341 | B86: BR01 | C86: =IFERROR(VLOOKUP(B86,Branches!A:B, 2, FALSE), B86&"(NOT FOUND)") -> Lekki Branch | D86: 45479 | E86: S001 | F86: =IFERROR(VLOOKUP(E86, Staff!A:B, 2, FALSE), E86&" (NOT FOUND)") -> Chika Nwankwo | G86: Electronics | H86: Wireless Earbuds | I86: 2 | J86: 2892.21 | K86: 0 | L86: Card | M86: Returning | N86: =IF(OR(I86="",J86=""),"",IF(OR(K86="", K86=0), I86*J86, (I86*J86)-(K86/100)*I86*J86)) -> 5784.42
A87: 5413 | B87: BR01 | C87: =IFERROR(VLOOKUP(B87,Branches!A:B, 2, FALSE), B87&"(NOT FOUND)") -> Lekki Branch | D87: 45538 | E87: S005 | F87: =IFERROR(VLOOKUP(E87, Staff!A:B, 2, FALSE), E87&" (NOT FOUND)") -> Funke Ajayi | G87: Personal Care | H87: Deodorant | I87: 3 | L87: Cash | M87: Returning | N87: =IF(OR(I87="",J87=""),"",IF(OR(K87="", K87=0), I87*J87, (I87*J87)-(K87/100)*I87*J87))
A88: 5147 | B88: BR03 | C88: =IFERROR(VLOOKUP(B88,Branches!A:B, 2, FALSE), B88&"(NOT FOUND)") -> GRA Branch | D88: 45314 | E88: S005 | F88: =IFERROR(VLOOKUP(E88, Staff!A:B, 2, FALSE), E88&" (NOT FOUND)") -> Funke Ajayi | G88: Electronics | H88: Phone Charger | I88: 2 | J88: 20517.81 | K88: 5 | L88: Transfer | M88: Returning | N88: =IF(OR(I88="",J88=""),"",IF(OR(K88="", K88=0), I88*J88, (I88*J88)-(K88/100)*I88*J88)) -> 38983.839
A89: 5480 | B89: BR03 | C89: =IFERROR(VLOOKUP(B89,Branches!A:B, 2, FALSE), B89&"(NOT FOUND)") -> GRA Branch | D89: 45351 | E89: S002 | F89: =IFERROR(VLOOKUP(E89, Staff!A:B, 2, FALSE), E89&" (NOT FOUND)") -> Tobi Adewale | G89: Groceries | H89: Tomato Paste | I89: 2 | K89: 0 | L89: Cash | M89: New | N89: =IF(OR(I89="",J89=""),"",IF(OR(K89="", K89=0), I89*J89, (I89*J89)-(K89/100)*I89*J89)) | O89: NO
A90: 5500 | B90: BR04 | C90: =IFERROR(VLOOKUP(B90,Branches!A:B, 2, FALSE), B90&"(NOT FOUND)") -> Sabon Gari Branch | D90: 45445 | E90: S006 | F90: =IFERROR(VLOOKUP(E90, Staff!A:B, 2, FALSE), E90&" (NOT FOUND)") -> Ibrahim Sani | G90: Personal Care | H90: Toothpaste | J90: 42248.05 | L90: Card | M90: New | N90: =IF(OR(I90="",J90=""),"",IF(OR(K90="", K90=0), I90*J90, (I90*J90)-(K90/100)*I90*J90))
A91: 5096 | B91: BR03 | C91: =IFERROR(VLOOKUP(B91,Branches!A:B, 2, FALSE), B91&"(NOT FOUND)") -> GRA Branch | D91: 45343 | E91: S006 | F91: =IFERROR(VLOOKUP(E91, Staff!A:B, 2, FALSE), E91&" (NOT FOUND)") -> Ibrahim Sani | G91: Groceries | H91: Sugar (1kg) | J91: 26419.26 | K91: 10 | L91: Cash | M91: New | N91: =IF(OR(I91="",J91=""),"",IF(OR(K91="", K91=0), I91*J91, (I91*J91)-(K91/100)*I91*J91)) | O91: YES
A92: 5279 | B92: BR01 | C92: =IFERROR(VLOOKUP(B92,Branches!A:B, 2, FALSE), B92&"(NOT FOUND)") -> Lekki Branch | D92: 45520 | E92: S002 | F92: =IFERROR(VLOOKUP(E92, Staff!A:B, 2, FALSE), E92&" (NOT FOUND)") -> Tobi Adewale | G92: Personal Care | H92: Toothpaste | I92: 4 | J92: 3763.73 | L92: Card | M92: Returning | N92: =IF(OR(I92="",J92=""),"",IF(OR(K92="", K92=0), I92*J92, (I92*J92)-(K92/100)*I92*J92)) -> 15054.92 | O92: YES
A93: 5093 | B93: BR04 | C93: =IFERROR(VLOOKUP(B93,Branches!A:B, 2, FALSE), B93&"(NOT FOUND)") -> Sabon Gari Branch | D93: 45492 | E93: S002 | F93: =IFERROR(VLOOKUP(E93, Staff!A:B, 2, FALSE), E93&" (NOT FOUND)") -> Tobi Adewale | G93: Home & Kitchen | H93: Storage Containers | J93: 16169.56 | K93: 0 | L93: Transfer | M93: Returning | N93: =IF(OR(I93="",J93=""),"",IF(OR(K93="", K93=0), I93*J93, (I93*J93)-(K93/100)*I93*J93)) | O93: YES
A94: 5030 | B94: BR02 | C94: =IFERROR(VLOOKUP(B94,Branches!A:B, 2, FALSE), B94&"(NOT FOUND)") -> Wuse Branch | D94: 45411 | E94: S001 | F94: =IFERROR(VLOOKUP(E94, Staff!A:B, 2, FALSE), E94&" (NOT FOUND)") -> Chika Nwankwo | G94: Electronics | H94: HDMI Cable | I94: 2 | K94: 10 | L94: Cash | M94: New | N94: =IF(OR(I94="",J94=""),"",IF(OR(K94="", K94=0), I94*J94, (I94*J94)-(K94/100)*I94*J94)) | O94: NO
A95: 5436 | B95: BR04 | C95: =IFERROR(VLOOKUP(B95,Branches!A:B, 2, FALSE), B95&"(NOT FOUND)") -> Sabon Gari Branch | D95: 45403 | E95: S003 | F95: =IFERROR(VLOOKUP(E95, Staff!A:B, 2, FALSE), E95&" (NOT FOUND)") -> Halima Yusuf | G95: Electronics | H95: Phone Charger | J95: 18697.12 | L95: Cash | M95: Returning | N95: =IF(OR(I95="",J95=""),"",IF(OR(K95="", K95=0), I95*J95, (I95*J95)-(K95/100)*I95*J95)) | O95: NO
A96: 5432 | B96: BR05 | C96: =IFERROR(VLOOKUP(B96,Branches!A:B, 2, FALSE), B96&"(NOT FOUND)") -> Bodija Branch | D96: 45507 | E96: S001 | F96: =IFERROR(VLOOKUP(E96, Staff!A:B, 2, FALSE), E96&" (NOT FOUND)") -> Chika Nwankwo | G96: Personal Care | H96: Soap Bar | J96: 26200.63 | K96: 5 | L96: Cash | M96: Returning | N96: =IF(OR(I96="",J96=""),"",IF(OR(K96="", K96=0), I96*J96, (I96*J96)-(K96/100)*I96*J96)) | O96: NO
A97: 5098 | B97: BR02 | C97: =IFERROR(VLOOKUP(B97,Branches!A:B, 2, FALSE), B97&"(NOT FOUND)") -> Wuse Branch | D97: 45365 | E97: S008 | F97: =IFERROR(VLOOKUP(E97, Staff!A:B, 2, FALSE), E97&" (NOT FOUND)") -> Ronke Bakare | G97: Electronics | H97: Phone Charger | I97: 4 | L97: Card | M97: Returning | N97: =IF(OR(I97="",J97=""),"",IF(OR(K97="", K97=0), I97*J97, (I97*J97)-(K97/100)*I97*J97)) | O97: NO
A98: 5146 | B98: BR02 | C98: =IFERROR(VLOOKUP(B98,Branches!A:B, 2, FALSE), B98&"(NOT FOUND)") -> Wuse Branch | D98: 45457 | E98: S002 | F98: =IFERROR(VLOOKUP(E98, Staff!A:B, 2, FALSE), E98&" (NOT FOUND)") -> Tobi Adewale | G98: Electronics | H98: Wireless Earbuds | I98: 5 | L98: Card | M98: Returning | N98: =IF(OR(I98="",J98=""),"",IF(OR(K98="", K98=0), I98*J98, (I98*J98)-(K98/100)*I98*J98)) | O98: YES
A99: 5411 | B99: BR05 | C99: =IFERROR(VLOOKUP(B99,Branches!A:B, 2, FALSE), B99&"(NOT FOUND)") -> Bodija Branch | D99: 45331 | E99: S001 | F99: =IFERROR(VLOOKUP(E99, Staff!A:B, 2, FALSE), E99&" (NOT FOUND)") -> Chika Nwankwo | G99: Groceries | H99: Rice (5kg) | I99: 1 | J99: 40070.51 | K99: 15 | L99: Card | M99: Returning | N99: =IF(OR(I99="",J99=""),"",IF(OR(K99="", K99=0), I99*J99, (I99*J99)-(K99/100)*I99*J99)) -> 34059.933 | O99: YES
A100: 5183 | B100: BR02 | C100: =IFERROR(VLOOKUP(B100,Branches!A:B, 2, FALSE), B100&"(NOT FOUND)") -> Wuse Branch | D100: 45476 | E100: S001 | F100: =IFERROR(VLOOKUP(E100, Staff!A:B, 2, FALSE), E100&" (NOT FOUND)") -> Chika Nwankwo | G100: Groceries | H100: Rice (5kg) | I100: 2 | J100: 40231.34 | K100: 5 | L100: Cash | M100: Returning | N100: =IF(OR(I100="",J100=""),"",IF(OR(K100="", K100=0), I100*J100, (I100*J100)-(K100/100)*I100*J100)) -> 76439.546 | O100: YES
...

Sheet Pivot_Summary
B1: TOTAL REVENUE BY BRANCH | M1: BEST AND WORST PERFORMERS
B2: Row Labels | C2: Sum of Total_Sale | M2: Row Labels | N2: Sum of Total_Sale
B3: Bodija Branch | C3: 3652522.9 | M3: Electronics | N3: 5633411.9
B4: GRA Branch | C4: 2623758.5 | M4: Groceries | N4: 4074959.1
B5: Lekki Branch | C5: 4225729.8 | M5: Home & Kitchen | N5: 3034480.5
B6: Sabon Gari Branch | C6: 2742787.6 | M6: Personal Care | N6: 4694020.9
B7: Wuse Branch | C7: 3915249.8 | M7: Grand Total | N7: 17436872
B8: BRXX(NOT FOUND) | C8: 72170.34
B9: BR09(NOT FOUND) | C9: 0
B10: BR12(NOT FOUND) | C10: 204653.5
B11: Grand Total | C11: 17436872
B17: SALES GENERATED BY STAFFS | E17: NEW VS RETURNING CUSTOMER
B18: Row Labels | C18: Sum of Total_Sale | E18: NEW
B19: Chika Nwankwo | C19: 0.11509029 | E19: =AVERAGEIF(Cleaned_Transactions!M:M, "NEW", Cleaned_Transactions!N:N) -> 60077.227
B20: Ekene Obi | C20: 0.14585285 | E20: RETURNING
B21: Funke Ajayi | C21: 0.11734203 | E21: =AVERAGEIF(Cleaned_Transactions!M:M, "RETURNING", Cleaned_Transactions!N:N) -> 65143.982
B22: Halima Yusuf | C22: 0.11757613
B23: Ibrahim Sani | C23: 0.12698752 | N23: Row Labels | O23: Sum of Total_Sale
B24: Kelechi Umeh | C24: 0.10045825 | O24: 1962718.4
B25: Ronke Bakare | C25: 0.15408286 | N25: NO | O25: 7902444.7
B26: Tobi Adewale | C26: 0.1022318 | N26: YES | O26: 7571709.3
B27: S099 (NOT FOUND) | C27: 0.002624992 | N27: Grand Total | O27: 17436872
B28: S100 (NOT FOUND) | C28: 0.014373226
B29: SXXX (NOT FOUND) | C29: 0.003380058
B30: Grand Total | C30: 1

Sheet Branches
A1: branch_code | B1: branch_name | C1: city
A2: BR01 | B2: Lekki Branch | C2: Lagos
A3: BR02 | B3: Wuse Branch | C3: Abuja
A4: BR03 | B4: GRA Branch | C4: Port Harcourt
A5: BR04 | B5: Sabon Gari Branch | C5: Kano
A6: BR05 | B6: Bodija Branch | C6: Ibadan

Sheet Staff
A1: staff_id | B1: staff_name | C1: department
A2: S001 | B2: Chika Nwankwo | C2: Sales
A3: S002 | B3: Tobi Adewale | C3: Sales
A4: S003 | B4: Halima Yusuf | C4: Sales
A5: S004 | B5: Ekene Obi | C5: Sales
A6: S005 | B6: Funke Ajayi | C6: Sales
A7: S006 | B7: Ibrahim Sani | C7: Sales
A8: S007 | B8: Kelechi Umeh | C8: Sales
A9: S008 | B9: Ronke Bakare | C9: Sales
